<?xml version="1.0" encoding="utf-8" ?>
<dwsync>
<file name="insert_main.php" server="ec2-3-134-86-72.us-east-2.compute.amazonaws.com//var/www/html/" local="133258884199895541" remote="133258884320000000" Dst="2" />
<file name="modify_insert_main.php" server="ec2-3-134-86-72.us-east-2.compute.amazonaws.com//var/www/html/" local="133257126383691697" remote="133257127350000000" Dst="2" />
<file name="modify_main.php" server="ec2-3-134-86-72.us-east-2.compute.amazonaws.com//var/www/html/" local="133258885126311921" remote="133258885210000000" Dst="2" />
<file name="modify_manufacturer.php" server="ec2-3-134-86-72.us-east-2.compute.amazonaws.com//var/www/html/" local="133258905146378204" remote="133258905180000000" Dst="2" />
<file name="modify_type.php" server="ec2-3-134-86-72.us-east-2.compute.amazonaws.com//var/www/html/" local="133258902010000000" remote="133258903950000000" Dst="2" />
<file name="modify_device.php" server="ec2-3-134-86-72.us-east-2.compute.amazonaws.com//var/www/html/" local="133258906550321876" remote="133258906630000000" Dst="2" />
<file name="insert_manu.php" server="ec2-3-134-86-72.us-east-2.compute.amazonaws.com//var/www/html/" local="133258905549071681" remote="133258906620000000" Dst="2" />
<file name="insert_type.php" server="ec2-3-134-86-72.us-east-2.compute.amazonaws.com//var/www/html/" local="133258904499648609" remote="133258904610000000" Dst="2" />
<file name="insert_device.php" server="ec2-3-134-86-72.us-east-2.compute.amazonaws.com//var/www/html/" local="133258904557871858" remote="133258904610000000" Dst="2" />
</dwsync>